sws_webstuff/__init__.py
sws_webstuff/_version.py
sws_webstuff/alert_class.py
sws_webstuff/alert_type_enum.py
sws_webstuff/misc.py
sws_webstuff/modal_class.py
sws_webstuff/modal_type_enum.py
sws_webstuff/redirect_class.py
sws_webstuff/languages/__init__.py
sws_webstuff/languages/english.py
sws_webstuff/languages/german.py
sws_webstuff/languages/lang_dict.py
sws_webstuff-0.0.4.dist-info/LICENSE
sws_webstuff-0.0.4.dist-info/METADATA
sws_webstuff-0.0.4.dist-info/WHEEL
sws_webstuff-0.0.4.dist-info/top_level.txt
sws_webstuff-0.0.4.dist-info/RECORD
