Metadata-Version: 2.1
Name: sws-webstuff
Version: 0.0.4
Summary: Some small things for Web Related stuff
Home-page: https://github.com/Aurvandill137/sws_webstuff
Author: Ole Hannemann
Author-email: cerberus885@gmail.com
License: MIT
Platform: UNKNOWN
Classifier: Programming Language :: Python :: 3.0
Classifier: Programming Language :: Python :: 3.9
Classifier: Development Status :: 5 - Production/Stable
Classifier: License :: OSI Approved :: MIT License
Requires-Dist: setuptools (>=45.0)
